{"cameraMode":{"drawMode":0,"name":"Shaded","section":"Shading Mode"},"sceneLighting":true,"audioPlay":false,"sceneViewState":{"m_AlwaysRefresh":false,"showFog":true,"showSkybox":false,"showFlares":true,"showImageEffects":true,"showParticleSystems":true,"showVisualEffectGraphs":true,"m_FxEnabled":true},"in2DMode":false,"pivot":{"x":1.8118743896484376,"y":0.5031747817993164,"z":1.644688606262207},"rotation":{"x":-0.1122148334980011,"y":0.8872612714767456,"z":-0.2997609078884125,"w":-0.3321448266506195},"size":11.443221092224121,"orthographic":false}